albumGet/__init__.py
albumGet/main.py
album_get-0.0.0.dist-info/licenses/LICENSE
album_get-0.0.0.dist-info/METADATA
album_get-0.0.0.dist-info/WHEEL
album_get-0.0.0.dist-info/entry_points.txt
album_get-0.0.0.dist-info/top_level.txt
album_get-0.0.0.dist-info/RECORD
