Metadata-Version: 2.4
Name: album-get
Version: 0.0.0
Summary: Download albums by their name using MusicBrainz API and yt-dlp
Author-email: Christian Haastrup <chaastrup865@gmail.com>
License-File: LICENSE
Requires-Dist: requests
Requires-Dist: yt-dlp
Requires-Dist: mutagen
Requires-Dist: ffmpeg
Dynamic: license-file
